{"rdapConformance":["rdap_level_0","nro_rdap_profile_0","nro_rdap_profile_asn_flat_0"],"notices":[{"title":"ABOUT","description":["This is the AfriNIC RDAP server."],"links":[{"value":"https://rdap.afrinic.net/rdap/autnum/AS33771","rel":"describedby","href":"https://www.afrinic.net/support/whois-db/reference-manual","hreflang":["en"],"type":"text/html","title":"AFRINIC Database Reference Manual","media":"screen"}]},{"title":"Terms and Conditions","description":["This is the AFRINIC Database query service. The objects are in RDAP format."],"links":[{"value":"https://rdap.afrinic.net/rdap/autnum/AS33771","rel":"terms-of-service","href":"https://afrinic.net/whois/terms","type":"text/html"}]},{"title":"Whois Inaccuracy Reporting","description":["If you see inaccuracies in the results, please visit: "],"links":[{"value":"https://rdap.afrinic.net/rdap/autnum/AS33771","rel":"inaccuracy-report","href":"https://www.afrinic.net/support/whois-db/reference-manual","type":"text/html","title":"AFRINIC WHOIS Inaccuracy Report"}]},{"title":"jCard sunset end","description":["2023-12-31T23:59:59Z"],"links":[{"value":"https://rdap.afrinic.net/rdap/autnum/AS33771","rel":"related","href":"https://www.ietf.org/id/draft-ietf-regext-rdap-jscontact-12.html","type":"text/html","title":"jCard deprecation and replacement with JSContact Card"},{"value":"https://rdap.afrinic.net/rdap/autnum/AS33771","rel":"alternate","href":"https://rdap.afrinic.net/rdap/autnum/AS33771?jscard=1","type":"application/rdap+json","title":"JSContact Card version"}]},{"title":"jCard deprecation end","description":["2022-12-31T23:59:59Z"],"links":[{"value":"https://rdap.afrinic.net/rdap/autnum/AS33771","rel":"related","href":"https://www.ietf.org/id/draft-ietf-regext-rdap-jscontact-12.html","type":"text/html","title":"jCard deprecation and replacement with JSContact Card"},{"value":"https://rdap.afrinic.net/rdap/autnum/AS33771","rel":"alternate","href":"https://rdap.afrinic.net/rdap/autnum/AS33771?jscard=1","type":"application/rdap+json","title":"JSContact Card version"}]}],"handle":"AS33771","lang":"en","remarks":[{"title":"Remark","description":["Import/Export rules:"]},{"title":"Remark","description":["from AS12491 accept any"]},{"title":"Remark","description":["to AS12491 announce AS33771"]},{"title":"Remark","description":["from AS12455 accept any"]},{"title":"Remark","description":["to AS12455 announce AS33771"]}],"links":[{"value":"https://rdap.afrinic.net/rdap/autnum/AS33771","rel":"self","href":"https://rdap.afrinic.net/rdap/autnum/AS33771"}],"events":[{"eventAction":"registration","eventDate":"2005-04-11T15:04:00Z"},{"eventAction":"last changed","eventDate":"2025-11-11T05:07:00Z"}],"status":["active"],"port43":"whois.afrinic.net","name":"ORG-SL70-AFRINIC","entities":[{"handle":"CM107-AFRINIC","lang":"en","links":[{"value":"https://rdap.afrinic.net/rdap/entity/CM107-AFRINIC","rel":"self","href":"https://rdap.afrinic.net/rdap/entity/CM107-AFRINIC"}],"status":["active"],"port43":"whois.afrinic.net","vcardArray":["vcard",[["version",{},"text","4.0"],["kind",{},"text","individual"],["fn",{},"text","Castrol Mutinda"],["tel",{"type":"work"},"text","tel:+254-711-319283"],["email",{},"text","cmutinda2@safaricom.co.ke"],["adr",{"label":"Nairobi\nKenya"},"text",["Nairobi","Kenya","","","","",""]]]],"roles":["administrative"],"objectClassName":"entity"},{"handle":"GK40-AFRINIC","lang":"en","links":[{"value":"https://rdap.afrinic.net/rdap/entity/GK40-AFRINIC","rel":"self","href":"https://rdap.afrinic.net/rdap/entity/GK40-AFRINIC"}],"status":["active"],"port43":"whois.afrinic.net","vcardArray":["vcard",[["version",{},"text","4.0"],["kind",{},"text","individual"],["fn",{},"text","Geoffry Kipchumba"],["tel",{"type":"work"},"text","tel:+254-722-000000"],["email",{},"text","GKIPCHUMBA@Safaricom.co.ke"],["adr",{"label":"Safaricom House\nNairobi\nKenya"},"text",["Safaricom House","Nairobi","Kenya","","","",""]]]],"roles":["administrative","technical"],"objectClassName":"entity"},{"handle":"ORG-SL70-AFRINIC","lang":"en","remarks":[{"title":"Remark","description":["data has been transferred from RIPE Whois Database 20050221"]}],"links":[{"value":"https://rdap.afrinic.net/rdap/entity/ORG-SL70-AFRINIC","rel":"self","href":"https://rdap.afrinic.net/rdap/entity/ORG-SL70-AFRINIC"}],"status":["active"],"port43":"whois.afrinic.net","vcardArray":["vcard",[["version",{},"text","4.0"],["kind",{},"text","org"],["fn",{},"text","Safaricom Limited"],["tel",{"type":"work"},"text","tel:+254-722-727615"],["tel",{"type":"work"},"text","tel:+254-772-004048"],["tel",{"type":"work"},"text","tel:+254-722-002222"],["tel",{"type":"work"},"text","tel:+254-725-347648"],["email",{},"text","amasila@safaricom.co.ke"],["adr",{"label":"WAIYAKI WAY\nPO BOX 66827 - 00800\nNAIROBI"},"text",["WAIYAKI WAY","PO BOX 66827 - 00800","NAIROBI","","","",""]]]],"roles":["registrant"],"objectClassName":"entity"},{"handle":"SNN3-AFRINIC","lang":"en","links":[{"value":"https://rdap.afrinic.net/rdap/entity/SNN3-AFRINIC","rel":"self","href":"https://rdap.afrinic.net/rdap/entity/SNN3-AFRINIC"}],"status":["active"],"port43":"whois.afrinic.net","vcardArray":["vcard",[["version",{},"text","4.0"],["kind",{},"text","individual"],["fn",{},"text","Stephen Njoroge Njuguna"],["tel",{"type":"work"},"text","tel:+254-727-371910"],["email",{},"text","SNjuguna@Safaricom.co.ke"],["adr",{"label":"Waiyaki Way\nNairobi 00800\nKenya"},"text",["Waiyaki Way","Nairobi 00800","Kenya","","","",""]]]],"roles":["administrative"],"objectClassName":"entity"},{"handle":"JM27-afrinic","lang":"en","links":[{"value":"https://rdap.afrinic.net/rdap/entity/JM27-afrinic","rel":"self","href":"https://rdap.afrinic.net/rdap/entity/JM27-afrinic"}],"status":["active"],"port43":"whois.afrinic.net","vcardArray":["vcard",[["version",{},"text","4.0"],["kind",{},"text","individual"],["fn",{},"text","John Muita"],["tel",{"type":"work"},"text","tel:+254-722-002829"],["tel",{"type":"work"},"text","tel:+254-722-003272"],["email",{},"text","CorePSPlanningTeam@Safaricom.co.ke"],["adr",{"label":"P.O Box 66827, 00800\nNairobi\nKenya"},"text",["P.O Box 66827, 00800","Nairobi","Kenya","","","",""]]]],"roles":["administrative","technical"],"objectClassName":"entity"},{"handle":"EA99-AFRINIC","lang":"en","links":[{"value":"https://rdap.afrinic.net/rdap/entity/EA99-AFRINIC","rel":"self","href":"https://rdap.afrinic.net/rdap/entity/EA99-AFRINIC"}],"status":["active"],"port43":"whois.afrinic.net","vcardArray":["vcard",[["version",{},"text","4.0"],["kind",{},"text","individual"],["fn",{},"text","Eric Angwenyi"],["tel",{"type":"work"},"text","tel:+254-726-949826"],["email",{},"text","enyakundi@safaricom.co.ke"],["adr",{"label":"Safaricom House\nPostal Code 62827\nNairobi\nKenya"},"text",["Safaricom House","Postal Code 62827","Nairobi","Kenya","","",""]]]],"roles":["administrative","technical"],"objectClassName":"entity"},{"handle":"BS56-AFRINIC","lang":"en","links":[{"value":"https://rdap.afrinic.net/rdap/entity/BS56-AFRINIC","rel":"self","href":"https://rdap.afrinic.net/rdap/entity/BS56-AFRINIC"}],"status":["active"],"port43":"whois.afrinic.net","vcardArray":["vcard",[["version",{},"text","4.0"],["kind",{},"text","individual"],["fn",{},"text","Business Support"],["tel",{"type":"work"},"text","tel:+254-722-003272"],["email",{},"text","support@safaricombusiness.co.ke"],["adr",{"label":"Nairobi Kenya"},"text",["Nairobi Kenya","","","","","",""]]]],"roles":["technical"],"objectClassName":"entity"},{"handle":"VK24-AFRINIC","lang":"en","links":[{"value":"https://rdap.afrinic.net/rdap/entity/VK24-AFRINIC","rel":"self","href":"https://rdap.afrinic.net/rdap/entity/VK24-AFRINIC"}],"status":["active"],"port43":"whois.afrinic.net","vcardArray":["vcard",[["version",{},"text","4.0"],["kind",{},"text","individual"],["fn",{},"text","Victor Kilei"],["tel",{"type":"work"},"text","tel:+254-725-403192"],["email",{},"text","vkitavi@safaricom.co.ke"],["adr",{"label":"Safaricom House\nPostal Code 62827\nNairobi\nKenya"},"text",["Safaricom House","Postal Code 62827","Nairobi","Kenya","","",""]]]],"roles":["administrative","technical"],"objectClassName":"entity"},{"handle":"VE6-AFRINIC","lang":"en","links":[{"value":"https://rdap.afrinic.net/rdap/entity/VE6-AFRINIC","rel":"self","href":"https://rdap.afrinic.net/rdap/entity/VE6-AFRINIC"}],"status":["active"],"port43":"whois.afrinic.net","vcardArray":["vcard",[["version",{},"text","4.0"],["kind",{},"text","individual"],["fn",{},"text","Vincent Etemesi"],["tel",{"type":"work"},"text","tel:+254-722-358432"],["email",{},"text","vetemesi@safaricom.co.ke"],["adr",{"label":"Safaricom House\nPostal Code 62827\nNairobi\nKenya"},"text",["Safaricom House","Postal Code 62827","Nairobi","Kenya","","",""]]]],"roles":["administrative","technical"],"objectClassName":"entity"},{"handle":"TR18-AFRINIC","lang":"en","links":[{"value":"https://rdap.afrinic.net/rdap/entity/TR18-AFRINIC","rel":"self","href":"https://rdap.afrinic.net/rdap/entity/TR18-AFRINIC"}],"status":["active"],"port43":"whois.afrinic.net","vcardArray":["vcard",[["version",{},"text","4.0"],["kind",{},"text","individual"],["fn",{},"text","Timothy Rutto"],["tel",{"type":"work"},"text","tel:+254-723-712399"],["email",{},"text","TKRUTTO@Safaricom.co.ke"],["adr",{"label":"PO BOX 66827 - 00800\nNairobi 00800\nKenya"},"text",["PO BOX 66827 - 00800","Nairobi 00800","Kenya","","","",""]]]],"roles":["administrative","technical"],"objectClassName":"entity"}],"startAutnum":33771,"endAutnum":33771,"objectClassName":"autnum"}